fireflyalgorithm/__init__.py
fireflyalgorithm/__main__.py
fireflyalgorithm/cli.py
fireflyalgorithm/fireflyalgorithm.py
fireflyalgorithm/problems.py
fireflyalgorithm-0.4.6.dist-info/LICENSE
fireflyalgorithm-0.4.6.dist-info/METADATA
fireflyalgorithm-0.4.6.dist-info/WHEEL
fireflyalgorithm-0.4.6.dist-info/entry_points.txt
fireflyalgorithm-0.4.6.dist-info/RECORD
