Metadata-Version: 2.1
Name: fireflyalgorithm
Version: 0.4.6
Summary: Implementation of Firefly Algorithm in Python
Home-page: https://github.com/firefly-cpp/FireflyAlgorithm
License: MIT
Keywords: computational intelligence,firefly algorithm,swarm intelligence,optimization
Author: Iztok Fister Jr.
Author-email: iztok@iztok-jr-fister.eu
Requires-Python: >=3.9,<3.14
Classifier: License :: OSI Approved :: MIT License
Classifier: Programming Language :: Python :: 3
Classifier: Programming Language :: Python :: 3.9
Classifier: Programming Language :: Python :: 3.10
Classifier: Programming Language :: Python :: 3.11
Classifier: Programming Language :: Python :: 3.12
Requires-Dist: numpy (>=1.26.1,<2.0.0)
Project-URL: Repository, https://github.com/firefly-cpp/FireflyAlgorithm
